x_make_test2_x/__init__.py
x_make_test2_x/x_cls_make_test2_x.py
x_make_test2_x-10.0.0.dist-info/METADATA
x_make_test2_x-10.0.0.dist-info/WHEEL
x_make_test2_x-10.0.0.dist-info/top_level.txt
x_make_test2_x-10.0.0.dist-info/RECORD
