Metadata-Version: 2.4
Name: x_make_test2_x
Version: 10.0.0
Summary: Test package 2.
Author-email: Roy GM <eye4357@outlook.com>
License-Expression: MIT
